cytestest/test1.py
cytestest/test2.py
cytestest-0.0.0.2.dist-info/METADATA
cytestest-0.0.0.2.dist-info/WHEEL
cytestest-0.0.0.2.dist-info/top_level.txt
cytestest-0.0.0.2.dist-info/RECORD
