Metadata-Version: 2.1
Name: cytestest
Version: 0.0.0.2
Summary: my fir test pack
Home-page: https://google.com
Author: uni
Author-email: tob@gmail.com
License: MIT
Requires-Python: >=3.7
